embedding_eval/__init__.py
embedding_eval/cli.py
embedding_eval/adapters/__init__.py
embedding_eval/adapters/embedding/__init__.py
embedding_eval/adapters/embedding/openai_embedding.py
embedding_eval/adapters/embedding/sentence_transformer.py
embedding_eval/adapters/vector/__init__.py
embedding_eval/adapters/vector/inmemory.py
embedding_eval/chunking/__init__.py
embedding_eval/chunking/strategies.py
embedding_eval/core/__init__.py
embedding_eval/core/models.py
embedding_eval/core/protocols.py
embedding_eval/evaluation/__init__.py
embedding_eval/evaluation/evaluators.py
embedding_eval/evaluation/validation.py
embedding_eval/optimization/__init__.py
embedding_eval/optimization/fair_comparison.py
embedding_eval-0.2.0.dist-info/METADATA
embedding_eval-0.2.0.dist-info/WHEEL
embedding_eval-0.2.0.dist-info/entry_points.txt
embedding_eval-0.2.0.dist-info/licenses/LICENSE
embedding_eval-0.2.0.dist-info/RECORD
