Metadata-Version: 2.4
Name: embedding-eval
Version: 0.2.0
Summary: Fair embedding model evaluation with independent parameter optimization
Project-URL: Homepage, https://github.com/swoodeng/embedding-eval
Project-URL: Documentation, https://github.com/swoodeng/embedding-eval#readme
Project-URL: Repository, https://github.com/swoodeng/embedding-eval
Project-URL: Issues, https://github.com/swoodeng/embedding-eval/issues
Author: swoodeng
License-Expression: MIT
License-File: LICENSE
Keywords: embeddings,evaluation,machine-learning,nlp,rag,retrieval
Classifier: Development Status :: 4 - Beta
Classifier: Intended Audience :: Developers
Classifier: Intended Audience :: Science/Research
Classifier: License :: OSI Approved :: MIT License
Classifier: Programming Language :: Python :: 3
Classifier: Programming Language :: Python :: 3.10
Classifier: Programming Language :: Python :: 3.11
Classifier: Programming Language :: Python :: 3.12
Classifier: Topic :: Scientific/Engineering :: Artificial Intelligence
Requires-Python: >=3.10
Requires-Dist: numpy>=1.24.0
Requires-Dist: sentence-transformers>=2.2.0
Requires-Dist: tiktoken>=0.5.0
Provides-Extra: all
Requires-Dist: openai>=1.0.0; extra == 'all'
Requires-Dist: pytest-cov>=4.0.0; extra == 'all'
Requires-Dist: pytest>=7.0.0; extra == 'all'
Requires-Dist: ruff>=0.1.0; extra == 'all'
Provides-Extra: dev
Requires-Dist: pytest-cov>=4.0.0; extra == 'dev'
Requires-Dist: pytest>=7.0.0; extra == 'dev'
Requires-Dist: ruff>=0.1.0; extra == 'dev'
Provides-Extra: openai
Requires-Dist: openai>=1.0.0; extra == 'openai'
